<lcgdict>
  <class name="HGCalTBRecHit" ClassVersion="0">
   <version ClassVersion="0" checksum="3094752182"/>
  </class>
  <class name="std::vector<HGCalTBRecHit>"/>
  <class name="edm::SortedCollection<HGCalTBRecHit,edm::StrictWeakOrdering<HGCalTBRecHit> >"/>
  <class name="edm::Wrapper<edm::SortedCollection<HGCalTBRecHit,edm::StrictWeakOrdering<HGCalTBRecHit> > >" />
  <class name="edm::Ref<edm::SortedCollection<HGCalTBRecHit,edm::StrictWeakOrdering<HGCalTBRecHit> >,HGCalTBRecHit,edm::refhelper::FindUsingAdvance<edm::SortedCollection<HGCalTBRecHit,edm::StrictWeakOrdering<HGCalTBRecHit> >,HGCalTBRecHit> >"/>
  <class name="edm::RefVector<edm::SortedCollection<HGCalTBRecHit,edm::StrictWeakOrdering<HGCalTBRecHit> >,HGCalTBRecHit,edm::refhelper::FindUsingAdvance<edm::SortedCollection<HGCalTBRecHit,edm::StrictWeakOrdering<HGCalTBRecHit> >,HGCalTBRecHit> >"/>
  <class name="edm::RefProd<edm::SortedCollection<HGCalTBRecHit,edm::StrictWeakOrdering<HGCalTBRecHit> > >"/>

  <class name="edm::Wrapper<HGCalTBRecHitCollection>"/>

  <class name="SKIROC2DigiCollection"/>
  <class name="edm::Wrapper<SKIROC2DigiCollection>"/>  
  
  <class name="edm::DetSet<HGCalTBRecHit>"/>
  <class name="edm::DetSetVector<HGCalTBRecHit>"/>
  <class name="std::vector<edm::DetSet<HGCalTBRecHit> >"/>
  <class name="std::vector<std::vector<edm::DetSet<HGCalTBRecHit> > >"/>
  <class name="edm::Wrapper<edm::DetSet<HGCalTBRecHit> >"/>
  <class name="edm::Wrapper<std::vector<edm::DetSet<HGCalTBRecHit> > >"/>
  <class name="edm::Wrapper<edm::DetSetVector<HGCalTBRecHit> >"/>
  <class name="edm::Wrapper<std::vector<std::vector<edm::DetSet<HGCalTBRecHit> > > >"/>

  <class name="edm::reftobase::Holder<CaloRecHit, edm::Ref<edm::SortedCollection<HGCalTBRecHit, edm::StrictWeakOrdering<HGCalTBRecHit> >, HGCalTBRecHit, edm::refhelper::FindUsingAdvance<edm::SortedCollection<HGCalTBRecHit, edm::StrictWeakOrdering<HGCalTBRecHit> >, HGCalTBRecHit> > >" />
</lcgdict>
